koppla/__init__.py
koppla/cli.py
koppla/config_manager.py
koppla/server.py
koppla-0.16.dist-info/licenses/LICENSE
koppla-0.16.dist-info/METADATA
koppla-0.16.dist-info/WHEEL
koppla-0.16.dist-info/entry_points.txt
koppla-0.16.dist-info/top_level.txt
koppla-0.16.dist-info/RECORD
