Metadata-Version: 2.4
Name: koppla
Version: 0.16
Summary: Koppla - Active Directory MCP Server
Home-page: https://github.com/ruudmens/koppla
Author: Rudy Mens - LazyAdmin.nl
License: MIT
License-File: LICENSE
Requires-Dist: ldap3
Requires-Dist: mcp
Requires-Dist: python-dotenv
Requires-Dist: cryptography
Dynamic: author
Dynamic: description
Dynamic: description-content-type
Dynamic: home-page
Dynamic: license
Dynamic: license-file
Dynamic: requires-dist
Dynamic: summary
